{
    "description": {
        "tag": "Колбасы, деликатесы",
        "name": "Колбасы сырокопченые"
    },
    "img": "url(public/products_cards/03.jpg)",
    "deals": {
        "tag": "подход",
        "title": "<h2>Номинант рейтинга <span>\"100 лучших товаров россии\"</span> 2013 года заслужил свою награду, ведь их колбасы производятся по оригинальной рецептуре</h2>",
        "description": "с использованием уникальных методов копчения (например на вишневых и облепиховых опилках), что делает вкус этих колбас по-настоящему волшебным и уже на протяжении 5 лет сохраняет качество на достойном уровне. Как и у других производителей, с которыми мы работаем, в колбасах ООО \"Вкус\" используются только натуральные ингридиенты."
    }
}